<setup>
    <pipe pip="1">
        <freq fre="2630">
            <branch gain_list="-6, -3">4</branch>
            <branch gain_list="-6, -3">5</branch>
        </freq>
        <freq fre="2655">
            <branch gain_list="-6, -3">4</branch>
            <branch gain_list="-6, -3">5</branch>
        </freq>
        <freq fre="2680">
            <branch gain_list="-6, -3">4</branch>
            <branch gain_list="-6, -3">5</branch>
        </freq>
    </pipe>
    <pipe pip="2">
        <freq fre="2120">
            <branch gain_list="-6, -3">4</branch>
            <branch gain_list="-6, -3">5</branch>
        </freq>
        <freq fre="2155">
            <branch gain_list="-6, -3">4</branch>
            <branch gain_list="-6, -3">5</branch>
        </freq>
        <freq fre="2190">
            <branch gain_list="-6, -3">4</branch>
            <branch gain_list="-6, -3">5</branch>
        </freq>
    </pipe>
</setup>